cryton_worker/__init__.py
cryton_worker/etc/__init__.py
cryton_worker/etc/config.py
cryton_worker/etc/systemd-service/cryton-executor.service
cryton_worker/lib/__init__.py
cryton_worker/lib/cli.py
cryton_worker/lib/consumer.py
cryton_worker/lib/empire.py
cryton_worker/lib/event.py
cryton_worker/lib/task.py
cryton_worker/lib/triggers/__init__.py
cryton_worker/lib/triggers/listener_base.py
cryton_worker/lib/triggers/listener_http.py
cryton_worker/lib/triggers/listener_msf.py
cryton_worker/lib/util/__init__.py
cryton_worker/lib/util/constants.py
cryton_worker/lib/util/exceptions.py
cryton_worker/lib/util/logger.py
cryton_worker/lib/util/module_util.py
cryton_worker/lib/util/util.py
cryton_worker/lib/worker.py
cryton_worker-2023.1.1.dist-info/entry_points.txt
cryton_worker-2023.1.1.dist-info/WHEEL
cryton_worker-2023.1.1.dist-info/METADATA
cryton_worker-2023.1.1.dist-info/LICENSE
cryton_worker-2023.1.1.dist-info/RECORD
