Metadata-Version: 2.1
Name: cryton-worker
Version: 2023.1.1
Summary: Attack scenario orchestrator for Cryton
Home-page: https://gitlab.ics.muni.cz/cryton
License: MIT
Keywords: cryton,worker,orchestrator,attacker
Author: Ivo Nutár
Author-email: nutar@ics.muni.cz
Maintainer: Jiří Rája
Maintainer-email: raja@ics.muni.cz
Requires-Python: >=3.8,<3.12
Classifier: License :: OSI Approved :: MIT License
Classifier: Programming Language :: Python :: 3
Classifier: Programming Language :: Python :: 3.8
Classifier: Programming Language :: Python :: 3.9
Classifier: Programming Language :: Python :: 3.10
Classifier: Programming Language :: Python :: 3.11
Requires-Dist: PyYAML (>=6.0,<7.0)
Requires-Dist: amqpstorm (>=2.10.4,<3.0.0)
Requires-Dist: bottle (>=0.12.19,<0.13.0)
Requires-Dist: click (>=8.1.2,<9.0.0)
Requires-Dist: paramiko (>=3.0.0,<4.0.0)
Requires-Dist: pyfiglet (>=0.8.post1,<0.9)
Requires-Dist: pymetasploit3 (>=1.0.3,<2.0.0)
Requires-Dist: python-dotenv (>=1.0.0,<2.0.0)
Requires-Dist: requests (>=2.28.2,<3.0.0)
Requires-Dist: schema (>=0.7.5,<0.8.0)
Requires-Dist: structlog (>=22.3.0,<23.0.0)
Requires-Dist: utinni (>=0.5.0,<0.6.0)
Project-URL: Documentation, https://cryton.gitlab-pages.ics.muni.cz/cryton-documentation/
Project-URL: Repository, https://gitlab.ics.muni.cz/cryton/cryton-worker
